pyautomail/__init__.py
pyautomail/__main__.py
pyautomail/cli.py
pyautomail/emailsender.py
pyautomail/manager.py
pyautomail/utils.py
pyautomail/config/__init__.py
pyautomail/config/config.py
pyautomail/storage/__init__.py
pyautomail/storage/model.py
pyautomail/storage/util.py
tests/__init__.py
tests/test_manager.py
tests/test_cli/__init__.py
tests/test_cli/test_cli.py
tests/test_cli/test_cli_init.py
tests/test_cli/test_cli_other.py
tests/test_cli/test_cli_register.py
pyautomail-1.7.0.7.dist-info/METADATA
pyautomail-1.7.0.7.dist-info/WHEEL
pyautomail-1.7.0.7.dist-info/entry_points.txt
pyautomail-1.7.0.7.dist-info/top_level.txt
pyautomail-1.7.0.7.dist-info/RECORD
