Metadata-Version: 2.1
Name: pyautomail
Version: 1.7.0.7
Summary: Automated Email Sending for Large Scale Email and Gmail Automation
Home-page: https://github.com/msinamsina/pyautomail
Author: Mohammad sina Allahkaram
Author-email: msinamsina@gmail.com
License: MIT
Project-URL: Bug Tracker, https://github.com/msinamsina/pyautomail/issues
Project-URL: Changelog, https://github.com/msinamsina/pyautomail/releases
Project-URL: Documentation, https://pyautomail.readthedocs.io/en/latest/
Project-URL: Source Code, https://github.com/msinamsina/pyautomail
Classifier: Programming Language :: Python :: 3
Classifier: License :: OSI Approved :: MIT License
Classifier: Operating System :: OS Independent
Requires-Python: >=3.7
Requires-Dist: sqlalchemy
Requires-Dist: sqlalchemy-utils
Requires-Dist: jinja2
Requires-Dist: pandas
Requires-Dist: coloredlogs
Requires-Dist: pytest
Requires-Dist: typer
